Workbook

Sheet COVER
D5: COMPANY NAME | E5: TATA MOTORS
D6: MADE BY | E6: ADITYARAJ SINGH RATHORE
D7: DATE | E7: 45966
D8: FINAL VALUATION RECOMMENDATION
D9: RECOMMENDATION

Sheet HIST_IS
B1: TATA MOTORS HISTORICAL INCOME STATEMENT
B2: ALL FIGURES IN INR MILLIONS
B3: Line Item | C3: FY20 | D3: FY21 | E3: FY22 | F3: FY23 | G3: FY24
A4: I | B4: Revenue from Operations | C4: 2610679.7 | D4: 2497947.5 | E4: 2784536.2 | F4: 3459669.7 | G4: 4340160
A5: II | B5: Other Income | C5: 29731.5 | D5: 26431.9 | E5: 30536.3 | F5: 46331.8 | G5: 56920
A6: III | B6: Total Income | C6: =C4+C5 -> 2640411.2 | D6: =D4+D5 -> 2524379.4 | E6: =E4+E5 -> 2815072.5 | F6: =F4+F5 -> 3506001.5 | G6: =G4+G5 -> 4397080
A7: IV | B7: Expenses
B8: Cost of materials consumed | C8: 1657151.1 | D8: 1413924.3 | E8: 1595980.6 | F8: 2082180.5 | G8: 2492780
B9: Purchases of products for sale | C9: 150078.2 | D9: 122500.9 | E9: 183747.7 | F9: 223069.5 | G9: 250430
B10: Changes in inventories of finished goods, wip,products for sale | C10: 15658.1 | D10: 46841.6 | E10: 15904.9 | F10: 47816.2 | G10: 15660
B11: Employee benefits expense | C11: 304386 | D11: 276484.8 | E11: 308085.2 | F11: 336547 | G11: 419900
B12: Finance costs | C12: 72433.3 | D12: 80971.7 | E12: 93118.6 | F12: 102254.8 | G12: 75940
B13: Compulsorily convertible preference share measured at Fair Value | E13: 144.5 | F13: 137.5 | G13: 480
B14: Foreign exchange (gain)/loss (net) | C14: 17387.4 | D14: 17321.5 | E14: 786.8 | F14: 1038.8 | G14: 150
B15: Depreciation and amortisation expense | C15: 239443.3 | D15: 235467.1 | E15: 248356.9 | F15: 248603.6 | G15: 272390
B16: Product development/engineering expenses | C16: 41884.9 | D16: 52266.3 | E16: 92095 | F16: 106619.6 | G16: 109590
B17: Other expenses | C17: 570874.6 | D17: 409219.7 | E17: 471338.5 | F17: 617859.6 | G17: 771980
B18: Amount transferred to capital and other account | C18: 175034 | D18: 128491.3 | E18: 143972.9 | F18: 184348.4 | G18: 267580
B19: TOTAL EXPENSES | C19: 2717496.6 | D19: 2491512 | E19: 2878810.8 | F19: 3491331.3 | G19: 4110400
B20: Cost of revenue (COGS) | C20: 1791571.2 | D20: 1583266.8 | E20: 1795633.2 | F20: 2257433.8 | G20: 2727550
B21: Gross Profit | C21: 848840 | D21: 941112.6 | E21: 1019439.3 | F21: 1248567.7 | G21: 1669530
B22: SG&A | C22: 875260.6 | D22: 685704.5 | E22: 779423.7 | F22: 954406.6 | G22: 1191880
A23: V | B23: EBITDA | C23: 211995.5 | D23: 185883.6 | E23: 224475.9 | F23: 380048.8 | G23: 726940
B24: EBIT | C24: =C23-C15 -> -27447.8 | D24: =D23-D15 -> -49583.5 | E24: =E23-E15 -> -23881 | F24: =F23-F15 -> 131445.2 | G24: =G23-G15 -> 454550
A25: VII | B25: Profit Before Taxes (PBT) | C25: =C24-C12 -> -99881.1 | D25: =D24-D12 -> -130555.2 | E25: =E24-E12 -> -116999.6 | F25: =F24-F12 -> 29190.4 | G25: =G24-G12 -> 378610
A26: VIII | B26: Total tax expense/(credit) (net) | C26: 3952.5 | D26: 25418.6 | E26: 42312.9 | F26: 7040.6 | G26: 40240
A27: XI | B27: Profit After Taxes (PAT) | C27: =C25-C26 -> -103833.6 | D27: =D25-D26 -> -155973.8 | E27: =E25-E26 -> -159312.5 | F27: =F25-F26 -> 22149.8 | G27: =G25-G26 -> 338370
A28: XIV | B28: Earnings per equity share (EPS)
B29: Basic EPS | C29: 34.88 | D29: 36.99 | E29: 29.88 | F29: 6.29 | G29: 81.95
B30: Diluted EPS | C30: 34.88 | D30: 36.99 | E30: 29.88 | F30: 6.29 | G30: 81.84

Sheet HIST_BS
A1: Tata Motors - Historical Balance Sheet
A2: (All figures in INR Millions)
A3: Line Item | B3: FY20 | C3: FY21 | D3: FY22 | E3: FY23 | F3: FY24
A4: ASSETS
A5: Non-Current Assets
A6: Property, Plant and Equipment | B6: 778830 | C6: 796400 | D6: 809000 | E6: 766410 | F6: 731250
A7: Intangible assets | B7: 699720 | C7: 651640 | D7: 579910 | E7: 566930 | F7: 650020
A8: Investments | B8: 54470 | C8: 56190 | D8: 66700 | E8: 75410 | F8: 76820
A9: Other Non-Current Assets | B9: 429360 | C9: 458150 | D9: 380810 | E9: 436780 | F9: 415470
A10: Total Non-Current Assets | B10: 1962380 | C10: 1962380 | D10: 1836420 | E10: 1845530 | F10: 1873560
A12: Current Assets
A13: Inventories | B13: 374570 | C13: 360890 | D13: 352400 | E13: 407550 | F13: 477880
A14: Trade receivables | B14: 111730 | C14: 126790 | D14: 124420 | E14: 157380 | F14: 169520
A15: Cash and cash equivalents | B15: 184680 | C15: 317000 | D15: 381590 | E15: 318870 | F15: 400150
A16: Other Current Assets | B16: 587850 | C16: 664200 | D16: 611370 | E16: 631480 | F16: 785530
A17: Total Current Assets | B17: 1258830 | C17: 1468880 | D17: 1469780 | E17: 1515280 | F17: 1833080
A19: TOTAL ASSETS | B19: =B10+B17 -> 3221210 | C19: =C10+C17 -> 3431260 | D19: =D10+D17 -> 3306200 | E19: =E10+E17 -> 3360810 | F19: =F10+F17 -> 3706640
A21: LIABILITIES & EQUITY
A22: Current Liabilities
A23: Borrowings (Short-term) | B23: 180410 | C23: 216630 | D23: 173780 | E23: 140670 | F23: 118130
A24: Trade payables | B24: 588120 | C24: 648490 | D24: 667430 | E24: 792140 | F24: 939780
A25: Other Current Liabilities | B25: 331200 | C25: 414860 | D25: 479880 | E25: 497190 | F25: 459100
A26: Total Current Liabilities | B26: 1099730 | C26: 1279980 | D26: 1321090 | E26: 1430000 | F26: 1517010
A28: Non-Current Liabilities
A29: Borrowings (Long-term) | B29: 1056560 | C29: 931130 | D29: 977590 | E29: 886960 | F29: 866880
A30: Other Non-Current Liabilities | B30: 426000 | C30: 651950 | D30: 519200 | E30: 517860 | F30: 391810
A31: Total Non-Current Liabilities | B31: 1482560 | C31: 1583080 | D31: 1496790 | E31: 1404820 | F31: 1258690
A33: Total Liabilities | B33: =B26+B31 -> 2582290 | C33: =C26+C31 -> 2863060 | D33: =D26+D31 -> 2817880 | E33: =E26+E31 -> 2834820 | F33: =F26+F31 -> 2775700
A35: Shareholders' Equity
A36: Share capital | B36: 7200 | C36: 7660 | D36: 7660 | E36: 7660 | F36: 7670
A37: Retained Earnings | B37: 358830 | C37: 165830 | D37: 229470 | E37: 252510 | F37: 552110
A38: Other Equity | B38: 272890 | C38: 394710 | D38: 251190 | E38: 265820 | F38: 371160
A39: Total Shareholders' Equity | B39: 638920 | C39: 568200 | D39: 488320 | E39: 525990 | F39: 930940
A41: TOTAL LIABILITIES & EQUITY | B41: =B33+B39 -> 3221210 | C41: =C33+C39 -> 3431260 | D41: =D33+D39 -> 3306200 | E41: =E33+E39 -> 3360810 | F41: =F33+F39 -> 3706640
A43: BALANCE CHECK | B43: =B19-B41 -> 0 | C43: =C19-C41 -> 0 | D43: =D19-D41 -> 0 | E43: =E19-E41 -> 0 | F43: =F19-F41 -> 0

Sheet HIST_CFS
A1: Tata Motors - Historical Cash Flow Statement
A2: (All figures in INR Millions)
A3: Line Item | B3: FY20 | C3: FY21 | D3: FY22 | E3: FY23 | F3: FY24
A4: Cash Flow Summary
A5: Net Cash from Operating Activities (CFO) | B5: -27080 | C5: 291901 | D5: 195520 | E5: 192589 | F5: 401950
A6: Net Cash from Investing Activities (CFI) | B6: -64613 | C6: -152218 | D6: -200111 | E6: -276246 | F6: -301210
A7: Net Cash from Financing Activities (CFF) | B7: 28292 | C7: -11024 | D7: 59924 | E7: -310486 | F7: -29330
A8: Net Change in Cash (CFO+CFI+CFF) | B8: =B5+B6+B7 -> -63401 | C8: =C5+C6+C7 -> 128659 | D8: =D5+D6+D7 -> 55333 | E8: =E5+E6+E7 -> -394143 | F8: =F5+F6+F7 -> 71410
A10: THE CASH CHECK
A11: Cash at Beginning of Year | B11: 250007 | C11: =HIST_BS!B15 -> 184680 | D11: =HIST_BS!C15 -> 317000 | E11: =HIST_BS!D15 -> 381590 | F11: =HIST_BS!E15 -> 318870
A12: Add: Net Change in Cash | B12: =B8 -> -63401 | C12: =C8 -> 128659 | D12: =D8 -> 55333 | E12: =E8 -> -394143 | F12: =F8 -> 71410
A13: Balancing Plug (FX, M&A, etc.) | B13: -1926 | C13: 3661 | D13: 9257 | E13: 331423 | F13: 9870
A14: Calculated Cash at End of Year | B14: =B11+B12+B13 -> 184680 | C14: =C11+C12+C13 -> 317000 | D14: =D11+D12+D13 -> 381590 | E14: =E11+E12+E13 -> 318870 | F14: =F11+F12+F13 -> 400150
A16: Cash from Balance Sheet (EoY) | B16: =HIST_BS!B15 -> 184680 | C16: =HIST_BS!C15 -> 317000 | D16: =HIST_BS!D15 -> 381590 | E16: =HIST_BS!E15 -> 318870 | F16: =HIST_BS!F15 -> 400150
A17: CHECK (Difference) | B17: =B14-B16 -> 0 | C17: =C14-C16 -> 0 | D17: =D14-D16 -> 0 | E17: =E14-E16 -> 0 | F17: =F14-F16 -> 0

Sheet ASSUMPTIONS
A1: Model Assumptions & Analysis
A2: Line Item | B2: Historical Analysis
B3: FY20 | C3: FY21 | D3: FY22 | E3: FY23 | F3: FY24
A4: INCOME STATEMENT
A5: Revenue Growth | B5: (N/A) | C5: =(HIST_IS!D6/HIST_IS!C6)-1 -> -0.043944595 | D5: =(HIST_IS!E6/HIST_IS!D6)-1 -> 0.11515428 | E5: =(HIST_IS!F6/HIST_IS!E6)-1 -> 0.24543915 | F5: =(HIST_IS!G6/HIST_IS!F6)-1 -> 0.25415805
A6: % of Total Revenue
A7: Cost of Revenue (COGS) | B7: =HIST_IS!C20/HIST_IS!C6 -> 0.67851977 | C7: =HIST_IS!D20/HIST_IS!D6 -> 0.62719051 | D7: =HIST_IS!E20/HIST_IS!E6 -> 0.63786393 | E7: =HIST_IS!F20/HIST_IS!F6 -> 0.64387702 | F7: =HIST_IS!G20/HIST_IS!G6 -> 0.62030939
A8: SG&A | B8: =HIST_IS!C22/HIST_IS!C6 -> 0.33148647 | C8: =HIST_IS!D22/HIST_IS!D6 -> 0.2716329 | D8: =HIST_IS!E22/HIST_IS!E6 -> 0.27687518 | E8: =HIST_IS!F22/HIST_IS!F6 -> 0.27222082 | F8: =HIST_IS!G22/HIST_IS!G6 -> 0.2710617
A9: Depreciation & Amortisation | B9: =HIST_IS!C15/HIST_IS!C6 -> 0.090684095 | C9: =HIST_IS!D15/HIST_IS!D6 -> 0.093277223 | D9: =HIST_IS!E15/HIST_IS!E6 -> 0.08822398 | E9: =HIST_IS!F15/HIST_IS!F6 -> 0.070908013 | F9: =HIST_IS!G15/HIST_IS!G6 -> 0.061947929
A10: Tax Rate (% of PBT) | B10: (N/A) | C10: (N/A) | D10: (N/A) | E10: =HIST_IS!F26/HIST_IS!F25 -> 0.24119574 | F10: =HIST_IS!G26/HIST_IS!G25 -> 0.10628351
A12: BALANCE SHEET
A13: % of Total Revenue
A14: Trade Receivables | B14: =HIST_BS!B14/HIST_IS!C6 -> 0.042315379 | C14: =HIST_BS!C14/HIST_IS!D6 -> 0.050226206 | D14: =HIST_BS!D14/HIST_IS!E6 -> 0.044197796 | E14: =HIST_BS!E14/HIST_IS!F6 -> 0.044888743 | F14: =HIST_BS!F14/HIST_IS!G6 -> 0.038552858
A15: Inventories | B15: =HIST_BS!B13/HIST_IS!C6 -> 0.14186048 | C15: =HIST_BS!C13/HIST_IS!D6 -> 0.14296187 | D15: =HIST_BS!D13/HIST_IS!E6 -> 0.12518328 | E15: =HIST_BS!E13/HIST_IS!F6 -> 0.11624353 | F15: =HIST_BS!F13/HIST_IS!G6 -> 0.10868122
A16: Trade Payables | B16: =HIST_BS!B24/HIST_IS!C6 -> 0.22273803 | C16: =HIST_BS!C24/HIST_IS!D6 -> 0.25689086 | D16: =HIST_BS!D24/HIST_IS!E6 -> 0.23709158 | E16: =HIST_BS!E24/HIST_IS!F6 -> 0.22593829 | F16: =HIST_BS!F24/HIST_IS!G6 -> 0.2137282
A18: CASH FLOW

Sheet ASSUMPTIONS VERIFIED
A2: Tata Motors - Final Model Assumptions
A3: All formulas are based on the 100% VERIFIED historical data.
A4: Line Item | B4: Historical Analysis | G4: Forecast Assumptions
B5: FY20 | C5: FY21 | D5: FY22 | E5: FY23 | F5: FY24 | G5: FY25 | H5: FY26 | I5: FY27 | J5: FY28 | K5: FY29
A6: INCOME STATEMENT
A7: Revenue Growth | B7: N/A | C7: -0.044 | D7: 0.1152 | E7: 0.2454 | F7: 0.2542 | G7: [Blue] | H7: [Blue] | I7: [Blue] | J7: [Blue] | K7: [Blue]
A9: % of Total Revenue
A10: Cost of Revenue (COGS) | B10: 0.6785 | C10: 0.6272 | D10: 0.6379 | E10: 0.6439 | F10: 0.6203 | G10: [Blue] | H10: [Blue] | I10: [Blue] | J10: [Blue] | K10: [Blue]
A11: Selling, General & Admin (SG&A) | B11: 0.3315 | C11: 0.2716 | D11: 0.2769 | E11: 0.2722 | F11: 0.2711 | G11: [Blue] | H11: [Blue] | I11: [Blue] | J11: [Blue] | K11: [Blue]
A12: Depreciation & Amortisation | B12: 0.0907 | C12: 0.0933 | D12: 0.0882 | E12: 0.0709 | F12: 0.062 | G12: [Blue] | H12: [Blue] | I12: [Blue] | J12: [Blue] | K12: [Blue]
A14: Effective Tax Rate (% of PBT) | B14: N/A | C14: N/A | D14: N/A | E14: N/A | F14: -0.3111 | G14: [Blue] | H14: [Blue] | I14: [Blue] | J14: [Blue] | K14: [Blue]
A16: CASH FLOW DRIVER
A17: CapEx as % of Revenue | B17: 0.1135 | C17: 0.0786 | D17: 0.0869 | E17: 0.0779 | F17: 0.0714 | G17: [Blue] | H17: [Blue] | I17: [Blue] | J17: [Blue] | K17: [Blue]
A19: WORKING CAPITAL (DAYS)
A20: Days Sales Outstanding (DSO) | B20: 19.68 | C20: 22.09 | D20: 24.22 | E20: 24.57 | F20: 22.5 | G20: [Blue] | H20: [Blue] | I20: [Blue] | J20: [Blue] | K20: [Blue]
A21: Days Inventory Outstanding (DIO) | B21: 74.83 | C21: 81.01 | D21: 89.81 | E21: 77.54 | F21: 64.97 | G21: [Blue] | H21: [Blue] | I21: [Blue] | J21: [Blue] | K21: [Blue]
A22: Days Payables Outstanding (DPO) | B22: 85.2 | C22: 104.93 | D22: 115.18 | E22: 92.99 | F22: 82.8 | G22: [Blue] | H22: [Blue] | I22: [Blue] | J22: [Blue] | K22: [Blue]

Sheet FORECAST

Sheet DCF
